album/__init__.py
album/__main__.py
album/api.py
album/argument_parsing.py
album/commandline.py
album/ci/__init__.py
album/ci/__main__.py
album/ci/argument_parsing.py
album/ci/commandline.py
album/ci/controller/__init__.py
album/ci/controller/release_manager.py
album/ci/controller/zenodo_manager.py
album/ci/utils/__init__.py
album/ci/utils/continuous_integration.py
album/ci/utils/zenodo_api.py
album/core/__init__.py
album/core/api/__init__.py
album/core/api/controller/__init__.py
album/core/api/controller/clone_manager.py
album/core/api/controller/controller.py
album/core/api/controller/deploy_manager.py
album/core/api/controller/environment_manager.py
album/core/api/controller/event_manager.py
album/core/api/controller/install_manager.py
album/core/api/controller/migration_manager.py
album/core/api/controller/resource_manager.py
album/core/api/controller/run_manager.py
album/core/api/controller/script_manager.py
album/core/api/controller/search_manager.py
album/core/api/controller/shared_downloads_manager.py
album/core/api/controller/state_manager.py
album/core/api/controller/task_manager.py
album/core/api/controller/test_manager.py
album/core/api/controller/collection/__init__.py
album/core/api/controller/collection/catalog_handler.py
album/core/api/controller/collection/collection_manager.py
album/core/api/controller/collection/solution_handler.py
album/core/api/model/__init__.py
album/core/api/model/catalog.py
album/core/api/model/catalog_index.py
album/core/api/model/catalog_updates.py
album/core/api/model/collection_index.py
album/core/api/model/collection_solution.py
album/core/api/model/configuration.py
album/core/api/model/database.py
album/core/api/model/event.py
album/core/api/model/mmversion.py
album/core/api/model/task.py
album/core/controller/__init__.py
album/core/controller/album_controller.py
album/core/controller/clone_manager.py
album/core/controller/deploy_manager.py
album/core/controller/environment_manager.py
album-0.12.0.dist-info/licenses/LICENSE
album-0.12.0.dist-info/METADATA
album-0.12.0.dist-info/WHEEL
album-0.12.0.dist-info/entry_points.txt
album-0.12.0.dist-info/top_level.txt
album-0.12.0.dist-info/RECORD
