Metadata-Version: 2.4
Name: album
Version: 0.12.0
Summary: album is a tool for unifying computational tools across frameworks, languages, and environments
Home-page: https://gitlab.com/album-app/album
Author: Kyle Harrington, Jan Philipp Albrecht, Deborah Schmidt
Maintainer: Kyle Harrington, Jan Philipp Albrecht, Deborah Schmidt
Maintainer-email: album@kyleharrington.com
License: MIT
Project-URL: Source, https://gitlab.com/album-app/album
Project-URL: Tracker, https://gitlab.com/album-app/album/issues
Keywords: virtual,environments,imaging,data analysis
Platform: any
Classifier: Development Status :: 3 - Alpha
Classifier: License :: OSI Approved :: MIT License
Classifier: Operating System :: MacOS :: MacOS X
Classifier: Operating System :: Microsoft :: Windows
Classifier: Operating System :: POSIX
Classifier: Programming Language :: Python :: 3.8
Classifier: Programming Language :: Python :: 3.9
Classifier: Programming Language :: Python :: Implementation :: PyPy
Classifier: Topic :: Utilities
Requires-Python: >=3.7
License-File: LICENSE
Requires-Dist: album-solution-api<0.8.0,>=0.7.0
Requires-Dist: album-environments<0.4.0,>=0.3.0
Requires-Dist: pyyaml>=5.4.1
Requires-Dist: validators>=0.18.2
Requires-Dist: gitpython>=3.1.13
Requires-Dist: requests>=2.25.1
Requires-Dist: pexpect>=4.8.0
Requires-Dist: jsonschema>=4.0.0
Requires-Dist: colorlog>=6.6.0
Requires-Dist: pywin32>=303; platform_system == "Windows"
Requires-Dist: packaging>=21.3
Requires-Dist: pre-commit>=2.20.0
Requires-Dist: pooch>=1.4.0
Dynamic: license-file
